{
    "id": "'623",
    "prerequisite": "Any divine class, must worship Avandra",
    "sourceRef": "Dragon Magazine 384",
    "name": "Fortune Blessed",
    "text": "Serendipity favors you. You have long proved a constant and loyal servant to Avandra by making her interests your own in your ongoing struggle against tyranny and in your willingness to explore the world and sample all it has to offer. Your virtuous soul and good works have won you the goddess’s favor, and although you know you were ever in her good graces, you realize you have only touched upon what is possible in her service.",
    "features": {
        "avandra'sLuck(11thLevel)": "Whenever you roll a natural 1 or 20 on an attack roll or saving throw during an encounter, you gain 1 luck token",
        "fortuneBlessedImplements(11thLevel)": "You can use any implements you would ordinarily use for divine powers with fortune blessed implement prayers",
        "luckyAction(11thLevel)": "Whenever you spend an action point to take an extra action, you can make a saving throw",
        "swiftLuck(16thLevel)": "The first time in each encounter that you roll a natural 18, 19, or 20 on an attack roll or saving throw, you can take an extra move action on your next turn"
    },
    "flavorText": "The odds are stacked in my favor."
}