{
    "id": "'177",
    "level": "14",
    "price": "4,000 gp",
    "keySkill": "Arcana",
    "sourceRef": "Manual of the Planes",
    "name": "Scramble Portal",
    "flavorText": "You alter the configuration of a teleportation circle or other portal so others cannot travel through it.",
    "category": "Warding",
    "time": "10 minutes",
    "duration": "Special",
    "text": "Scramble Portal allows you to alter the magic of a permanent portal, making it malfunction. For the ritual’s duration, the portal sends creatures passing through it to a random destination (DM’s discretion).  At the completion of the ritual, make a Arcana check. The result determines how long the portal remains scrambled.",
    "componentCost": "1,600 gp",
    "table": {
        "headers": [
            "Arcana Check Result",
            "Duration"
        ],
        "rows": [
            [
                "24 or lower",
                "1 hour"
            ],
            [
                "25–34",
                "8 hours"
            ],
            [
                "35–44",
                "1 day"
            ],
            [
                "45+",
                "7 days"
            ]
        ]
    }
}