{
  "Argent Strike": {
    "id": "'11149",
    "action": "Standard",
    "powerClass": "Argent Soul",
    "frequency": "Encounter",
    "level": "11",
    "name": "Argent Strike",
    "type": "Soul",
    "sourceRef": "Player's Handbook 3",
    "fullText": "\\r\\n\\r\\n<!DOCTYPE HTML>\\r\\n<html>\\r\\n<head id=\\\"Head1\\\"><title>\\r\\nArgent Strike\\r\\n</title><meta http-equiv=\\\"X-UA-Compatible\\\" content=\\\"IE=EmulateIE7\\\" /><link href=\\\"styles/detail.css\\\" media=\\\"screen\\\" rel=\\\"stylesheet\\\" type=\\\"text/css\\\" /><link href=\\\"styles/print.css\\\" media=\\\"print\\\" rel=\\\"stylesheet\\\" type=\\\"text/css\\\" /><link href=\\\"styles/mobile.css\\\" media=\\\"handheld\\\" rel=\\\"stylesheet\\\" type=\\\"text/css\\\" />\\r\\n    \\r\\n    \\r\\n    \\r\\n\\r\\n</head>\\r\\n<body>\\r\\n    <form name=\\\"form1\\\" method=\\\"post\\\" action=\\\"display.php?page=power&amp;id=11149\\\" id=\\\"form1\\\">\\r\\n<div>\\r\\n\\r\\n</div>\\r\\n\\r\\n\\r\\n    <div id=\\\"detail\\\">\\r\\n\\r\\n<h1 class=\\\"encounterpower\\\"><span class=\\\"level\\\">Argent Soul Attack 11</span>Argent Strike</h1><p class=\\\"flavor\\\"><i>Your weapon shines with silver light. When it strikes, your corona flares to revitalize an ally.</i></p><p class=\\\"powerstat\\\"><b>Encounter</b>&nbsp;&nbsp; <img src=\\\"images/bullet.gif\\\" alt=\\\"\\\"/>&nbsp;&nbsp;&nbsp;&nbsp; <b>Augmentable</b>, <b>Healing</b>, <b>Psionic</b>, <b>Radiant</b>, <b>Weapon</b><br/><b>Standard Action</b>&nbsp;&nbsp;&nbsp;&nbsp;&nbsp;&nbsp;<b>Melee</b> weapon</p><p class=\\\"powerstat\\\"><b>Target</b>: One creature</p><p class=\\\"powerstat\\\"><b>Attack</b>: Charisma vs. AC</p><p class=\\\"flavor\\\"><b>Hit</b>: 1[W] + Charisma modifier radiant damage, and one ally within 5 squares of you can both spend a healing surge and shift 1 square as a free action. If the ally doesn’t spend a healing surge, he or she gains 10 temporary hit points.</p><b>Augment 2</b><br/><p class=\\\"powerstat\\\"><b>Hit</b>: 2[W] + Charisma modifier radiant damage. Each ally within 3 squares of you can both spend a healing surge and shift 1 square as a free action. Any ally who doesn’t spend a healing surge gains 10 temporary hit points.</p><br/><p class=\\\"publishedIn\\\">Published in <a href=\\\"http://anonym.to/?http://www.wizards.com/default.asp?x=products/dndlist&brand=All&year=All&type=CoreGameProducts\\\" target=\\\"_new\\\">Player's Handbook 3</a>, page(s) 38.</p>\\r\\n    </div>\\r\\n    </form>\\r\\n</body>\\r\\n</html>\\r\\n\\r\\n<script type=\\\"text/javascript\\\">\\r\\n    if (document.all) {\\r\\n        if (document.documentMode != 9) {\\r\\n            var ar = document.getElementsByTagName('span'\\r\\n            for (var i = 0; i < ar.length; i++ ) {\\r\\n                var c = ar[i].attributes['class'].value;\\r\\n                if (c == 'milevel')\\r\\n                    ar[i].style.top = \\\"-24px\\\";\\r\\n                else if (c == 'miright')\\r\\n                    ar[i].style.top = \\\"-18px\\\";\\r\\n            }\\r\\n        }\\r\\n    }\\r\\n</script>\\r\\n",
    "flavor": "Your weapon shines with silver light. When it strikes, your corona flares to revitalize an ally.",
    "keywords": [
      "Augmentable, Healing, Psionic, Radiant, Weapon"
    ],
    "range": "Melee weapon<",
    "target": "One creature",
    "attack": "Charisma vs. AC",
    "onHit": "2[W] + Charisma modifier radiant damage. Each ally within 3 squares of you can both spend a healing surge and shift 1 square as a free action. Any ally who doesn’t spend a healing surge gains 10 temporary hit points."
  },
  "Argent Flood": {
    "id": "'11150",
    "action": "Standard",
    "powerClass": "Argent Soul",
    "frequency": "Daily",
    "level": "20",
    "name": "Argent Flood",
    "type": "Soul",
    "sourceRef": "Player's Handbook 3",
    "fullText": "\\r\\n\\r\\n<!DOCTYPE HTML>\\r\\n<html>\\r\\n<head id=\\\"Head1\\\"><title>\\r\\nArgent Flood\\r\\n</title><meta http-equiv=\\\"X-UA-Compatible\\\" content=\\\"IE=EmulateIE7\\\" /><link href=\\\"styles/detail.css\\\" media=\\\"screen\\\" rel=\\\"stylesheet\\\" type=\\\"text/css\\\" /><link href=\\\"styles/print.css\\\" media=\\\"print\\\" rel=\\\"stylesheet\\\" type=\\\"text/css\\\" /><link href=\\\"styles/mobile.css\\\" media=\\\"handheld\\\" rel=\\\"stylesheet\\\" type=\\\"text/css\\\" />\\r\\n    \\r\\n    \\r\\n    \\r\\n\\r\\n</head>\\r\\n<body>\\r\\n    <form name=\\\"form1\\\" method=\\\"post\\\" action=\\\"display.php?page=power&amp;id=11150\\\" id=\\\"form1\\\">\\r\\n<div>\\r\\n\\r\\n</div>\\r\\n\\r\\n\\r\\n    <div id=\\\"detail\\\">\\r\\n\\r\\n<h1 class=\\\"dailypower\\\"><span class=\\\"level\\\">Argent Soul Attack 20</span>Argent Flood</h1><p class=\\\"flavor\\\"><i>Your allies find new reserves in the silver light you unleash.</i></p><p class=\\\"powerstat\\\"><b>Daily</b>&nbsp;&nbsp; <img src=\\\"images/bullet.gif\\\" alt=\\\"\\\"/>&nbsp;&nbsp;&nbsp;&nbsp; <b>Healing</b>, <b>Psionic</b>, <b>Radiant</b>, <b>Weapon</b><br/><b>Standard Action</b>&nbsp;&nbsp;&nbsp;&nbsp;&nbsp;&nbsp;<b>Melee</b> weapon</p><p class=\\\"powerstat\\\"><b>Target</b>: One creature</p><p class=\\\"powerstat\\\"><b>Attack</b>: Charisma vs. AC</p><p class=\\\"flavor\\\"><b>Hit</b>: 4[W] + Charisma modifier radiant damage.</p><p class=\\\"powerstat\\\"><b>Effect</b>: Each ally within 5 squares of you can either spend a healing surge or gain temporary hit points equal to his or her healing surge value.</p><br/><p class=\\\"publishedIn\\\">Published in <a href=\\\"http://anonym.to/?http://www.wizards.com/default.asp?x=products/dndlist&brand=All&year=All&type=CoreGameProducts\\\" target=\\\"_new\\\">Player's Handbook 3</a>, page(s) 38.</p>\\r\\n    </div>\\r\\n    </form>\\r\\n</body>\\r\\n</html>\\r\\n\\r\\n<script type=\\\"text/javascript\\\">\\r\\n    if (document.all) {\\r\\n        if (document.documentMode != 9) {\\r\\n            var ar = document.getElementsByTagName('span'\\r\\n            for (var i = 0; i < ar.length; i++ ) {\\r\\n                var c = ar[i].attributes['class'].value;\\r\\n                if (c == 'milevel')\\r\\n                    ar[i].style.top = \\\"-24px\\\";\\r\\n                else if (c == 'miright')\\r\\n                    ar[i].style.top = \\\"-18px\\\";\\r\\n            }\\r\\n        }\\r\\n    }\\r\\n</script>\\r\\n",
    "flavor": "Your allies find new reserves in the silver light you unleash.",
    "keywords": [
      "Healing, Psionic, Radiant, Weapon"
    ],
    "range": "Melee weapon<",
    "target": "One creature",
    "attack": "Charisma vs. AC",
    "onHit": "4[W] + Charisma modifier radiant damage.",
    "effect": "Each ally within 5 squares of you can either spend a healing surge or gain temporary hit points equal to his or her healing surge value."
  },
  "Burgeoning Reserves": {
    "id": "'11151",
    "action": "Standard",
    "powerClass": "Argent Soul",
    "frequency": "Daily",
    "level": "12",
    "name": "Burgeoning Reserves",
    "type": "Soul",
    "sourceRef": "Player's Handbook 3",
    "fullText": "\\r\\n\\r\\n<!DOCTYPE HTML>\\r\\n<html>\\r\\n<head id=\\\"Head1\\\"><title>\\r\\nBurgeoning Reserves\\r\\n</title><meta http-equiv=\\\"X-UA-Compatible\\\" content=\\\"IE=EmulateIE7\\\" /><link href=\\\"styles/detail.css\\\" media=\\\"screen\\\" rel=\\\"stylesheet\\\" type=\\\"text/css\\\" /><link href=\\\"styles/print.css\\\" media=\\\"print\\\" rel=\\\"stylesheet\\\" type=\\\"text/css\\\" /><link href=\\\"styles/mobile.css\\\" media=\\\"handheld\\\" rel=\\\"stylesheet\\\" type=\\\"text/css\\\" />\\r\\n    \\r\\n    \\r\\n    \\r\\n\\r\\n</head>\\r\\n<body>\\r\\n    <form name=\\\"form1\\\" method=\\\"post\\\" action=\\\"display.php?page=power&amp;id=11151\\\" id=\\\"form1\\\">\\r\\n<div>\\r\\n\\r\\n</div>\\r\\n\\r\\n\\r\\n    <div id=\\\"detail\\\">\\r\\n\\r\\n<h1 class=\\\"dailypower\\\"><span class=\\\"level\\\">Argent Soul Utility 12</span>Burgeoning Reserves</h1><p class=\\\"flavor\\\"><i>Your touch restores vitality to a fallen comrade.</i></p><p class=\\\"powerstat\\\"><b>Daily</b>&nbsp;&nbsp; <img src=\\\"images/bullet.gif\\\" alt=\\\"\\\"/>&nbsp;&nbsp;&nbsp;&nbsp; <b>Healing</b>, <b>Psionic</b><br/><b>Standard Action</b>&nbsp;&nbsp;&nbsp;&nbsp;&nbsp;&nbsp;<b>Melee</b> 1</p><p class=\\\"powerstat\\\"><b>Target</b>: One dying ally</p><p class=\\\"flavor\\\"><b>Effect</b>: The target can spend a healing surge, and he or she gains regeneration 5 until the end of your next turn.</p><p class=\\\"powerstat\\\"><b>Sustain Minor</b>: The regeneration persists. You can sustain the regeneration only if the target is bloodied.</p><br/><p class=\\\"publishedIn\\\">Published in <a href=\\\"http://anonym.to/?http://www.wizards.com/default.asp?x=products/dndlist&brand=All&year=All&type=CoreGameProducts\\\" target=\\\"_new\\\">Player's Handbook 3</a>, page(s) 38.</p>\\r\\n    </div>\\r\\n    </form>\\r\\n</body>\\r\\n</html>\\r\\n\\r\\n<script type=\\\"text/javascript\\\">\\r\\n    if (document.all) {\\r\\n        if (document.documentMode != 9) {\\r\\n            var ar = document.getElementsByTagName('span'\\r\\n            for (var i = 0; i < ar.length; i++ ) {\\r\\n                var c = ar[i].attributes['class'].value;\\r\\n                if (c == 'milevel')\\r\\n                    ar[i].style.top = \\\"-24px\\\";\\r\\n                else if (c == 'miright')\\r\\n                    ar[i].style.top = \\\"-18px\\\";\\r\\n            }\\r\\n        }\\r\\n    }\\r\\n</script>\\r\\n",
    "flavor": "Your touch restores vitality to a fallen comrade.",
    "keywords": [
      "Healing, Psionic"
    ],
    "range": "Melee 1<",
    "target": "One dying ally",
    "effect": "The target can spend a healing surge, and he or she gains regeneration 5 until the end of your next turn.",
    "sustainMinor": "The regeneration persists. You can sustain the regeneration only if the target is bloodied."
  }
}