{
  "A Thousand Ways to Die": {
    "id": "'15821",
    "action": "No Action",
    "powerClass": "",
    "frequency": "Encounter",
    "level": "11",
    "name": "A Thousand Ways to Die",
    "type": "Berserker",
    "sourceRef": "Heroes of the Feywild",
    "fullText": "\\r\\n\\r\\n<!DOCTYPE HTML>\\r\\n<html>\\r\\n<head id=\\\"Head1\\\"><title>\\r\\nA Thousand Ways to Die\\r\\n</title><meta http-equiv=\\\"X-UA-Compatible\\\" content=\\\"IE=EmulateIE7\\\" /><link href=\\\"styles/detail.css\\\" media=\\\"screen\\\" rel=\\\"stylesheet\\\" type=\\\"text/css\\\" /><link href=\\\"styles/print.css\\\" media=\\\"print\\\" rel=\\\"stylesheet\\\" type=\\\"text/css\\\" /><link href=\\\"styles/mobile.css\\\" media=\\\"handheld\\\" rel=\\\"stylesheet\\\" type=\\\"text/css\\\" />\\r\\n    \\r\\n    \\r\\n    \\r\\n\\r\\n</head>\\r\\n<body>\\r\\n    <form name=\\\"form1\\\" method=\\\"post\\\" action=\\\"display.php?page=power&amp;id=15821\\\" id=\\\"form1\\\">\\r\\n<div>\\r\\n\\r\\n</div>\\r\\n\\r\\n\\r\\n    <div id=\\\"detail\\\">\\r\\n\\r\\n<h1 class=\\\"encounterpower\\\"><span class=\\\"level\\\">Deadly Berserker Attack 11</span>A Thousand Ways to Die</h1><p class=\\\"flavor\\\"><i>Your prowess in battle is well earned, and whether you’re raging at your enemies or in full control of your body, you have many ways to bring down your foe.</i></p><p class=\\\"powerstat\\\"><b>Encounter</b>&nbsp;&nbsp; <img src=\\\"images/bullet.gif\\\" alt=\\\"\\\"/>&nbsp;&nbsp;&nbsp;&nbsp; <b>Martial</b>, <b>Primal</b>, <b>Weapon</b><br/><b>No Action</b>&nbsp;&nbsp;&nbsp;&nbsp;&nbsp;&nbsp;<b>Special</b> </p><p class=\\\"powerstat\\\"><b>Trigger</b>: You hit a creature with a melee basic weapon attack or a barbarian at-will weapon attack power.</p><p class=\\\"powerstat\\\"><b>Target</b>: The creature you hit</p><p class=\\\"flavor\\\"><b>Effect</b>: The target takes 1[W] extra damage from the triggering attack. Additionally, choose one of the following effects.<br/>&nbsp;&nbsp;&nbsp;&nbsp;<img src=\\\"images/bullet.gif\\\" alt=\\\"\\\"/>&nbsp;&nbsp;&nbsp;&nbsp;The target is immobilized until the end of your next turn.<br/>&nbsp;&nbsp;&nbsp;&nbsp;<img src=\\\"images/bullet.gif\\\" alt=\\\"\\\"/>&nbsp;&nbsp;&nbsp;&nbsp;The target falls prone.</p><br/><p class=\\\"publishedIn\\\">Published in <a href=\\\"http://anonym.to/?http://www.wizards.com/dnd/Product.php?x=dnd/products/dndacc/317310000\\\" target=\\\"_new\\\">Heroes of the Feywild</a>, page(s) 116.</p>\\r\\n    </div>\\r\\n    </form>\\r\\n</body>\\r\\n</html>\\r\\n\\r\\n<script type=\\\"text/javascript\\\">\\r\\n    if (document.all) {\\r\\n        if (document.documentMode != 9) {\\r\\n            var ar = document.getElementsByTagName('span'\\r\\n            for (var i = 0; i < ar.length; i++ ) {\\r\\n                var c = ar[i].attributes['class'].value;\\r\\n                if (c == 'milevel')\\r\\n                    ar[i].style.top = \\\"-24px\\\";\\r\\n                else if (c == 'miright')\\r\\n                    ar[i].style.top = \\\"-18px\\\";\\r\\n            }\\r\\n        }\\r\\n    }\\r\\n</script>\\r\\n",
    "class": "Deadly Berserker",
    "flavor": "Your prowess in battle is well earned, and whether you’re raging at your enemies or in full control of your body, you have many ways to bring down your foe.",
    "keywords": [
      "Martial, Primal, Weapon"
    ],
    "range": "Special </p><p class=\"powerstat\">Trigger: You hit a creature with a melee basic weapon attack or a barbarian at-will weapon attack power.</p><p class=\"powerstat\">Target: The creature you hit</p><p class=\"flavor\">Effect: The target takes 1[W] extra damage from the triggering attack. Additionally, choose one of the following effects.",
    "trigger": "You hit a creature with a melee basic weapon attack or a barbarian at-will weapon attack power.",
    "target": "The creature you hit",
    "effect": "The target takes 1[W] extra damage from the triggering attack. Additionally, choose one of the following effects.<br/>&nbsp;&nbsp;&nbsp;&nbsp;<img src=\"images/bullet.gif\" alt=\"\"/>&nbsp;&nbsp;&nbsp;&nbsp;The target is immobilized until the end of your next turn.<br/>&nbsp;&nbsp;&nbsp;&nbsp;<img src=\"images/bullet.gif\" alt=\"\"/>&nbsp;&nbsp;&nbsp;&nbsp;The target falls prone."
  },
  "Surge of Strength": {
    "id": "'15822",
    "action": "Minor",
    "powerClass": "",
    "frequency": "Encounter",
    "level": "12",
    "name": "Surge of Strength",
    "type": "Berserker",
    "sourceRef": "Heroes of the Feywild",
    "fullText": "\\r\\n\\r\\n<!DOCTYPE HTML>\\r\\n<html>\\r\\n<head id=\\\"Head1\\\"><title>\\r\\nSurge of Strength\\r\\n</title><meta http-equiv=\\\"X-UA-Compatible\\\" content=\\\"IE=EmulateIE7\\\" /><link href=\\\"styles/detail.css\\\" media=\\\"screen\\\" rel=\\\"stylesheet\\\" type=\\\"text/css\\\" /><link href=\\\"styles/print.css\\\" media=\\\"print\\\" rel=\\\"stylesheet\\\" type=\\\"text/css\\\" /><link href=\\\"styles/mobile.css\\\" media=\\\"handheld\\\" rel=\\\"stylesheet\\\" type=\\\"text/css\\\" />\\r\\n    \\r\\n    \\r\\n    \\r\\n\\r\\n</head>\\r\\n<body>\\r\\n    <form name=\\\"form1\\\" method=\\\"post\\\" action=\\\"display.php?page=power&amp;id=15822\\\" id=\\\"form1\\\">\\r\\n<div>\\r\\n\\r\\n</div>\\r\\n\\r\\n\\r\\n    <div id=\\\"detail\\\">\\r\\n\\r\\n<h1 class=\\\"encounterpower\\\"><span class=\\\"level\\\">Deadly Berserker Utility 12</span>Surge of Strength</h1><p class=\\\"flavor\\\"><i>Even as your strength wanes and your health flags, you find a reserve of internal strength to continue the fight.</i></p><p class=\\\"powerstat\\\"><b>Encounter</b>&nbsp;&nbsp; <img src=\\\"images/bullet.gif\\\" alt=\\\"\\\"/>&nbsp;&nbsp;&nbsp;&nbsp; <b>Martial</b>, <b>Primal</b><br/><b>Minor Action</b>&nbsp;&nbsp;&nbsp;&nbsp;&nbsp;&nbsp;<b>Personal</b> </p><p class=\\\"flavor\\\"><b>Effect</b>: You gain temporary hit points equal to your healing surge value. If you are under the effect of your Berserker Fury, you gain the following benefit instead: When you make your next attack roll before the end of your next turn, roll twice and use either result.</p><br/><p class=\\\"publishedIn\\\">Published in <a href=\\\"http://anonym.to/?http://www.wizards.com/dnd/Product.php?x=dnd/products/dndacc/317310000\\\" target=\\\"_new\\\">Heroes of the Feywild</a>, page(s) 116.</p>\\r\\n    </div>\\r\\n    </form>\\r\\n</body>\\r\\n</html>\\r\\n\\r\\n<script type=\\\"text/javascript\\\">\\r\\n    if (document.all) {\\r\\n        if (document.documentMode != 9) {\\r\\n            var ar = document.getElementsByTagName('span'\\r\\n            for (var i = 0; i < ar.length; i++ ) {\\r\\n                var c = ar[i].attributes['class'].value;\\r\\n                if (c == 'milevel')\\r\\n                    ar[i].style.top = \\\"-24px\\\";\\r\\n                else if (c == 'miright')\\r\\n                    ar[i].style.top = \\\"-18px\\\";\\r\\n            }\\r\\n        }\\r\\n    }\\r\\n</script>\\r\\n",
    "class": "Deadly Berserker",
    "flavor": "Even as your strength wanes and your health flags, you find a reserve of internal strength to continue the fight.",
    "keywords": [
      "Martial, Primal"
    ],
    "range": "Personal </p><p class=\"flavor\">Effect: You gain temporary hit points equal to your healing surge value. If you are under the effect of your Berserker Fury, you gain the following benefit instead: When you make your next attack roll before the end of your next turn, roll twice and use either result.</p>",
    "effect": "You gain temporary hit points equal to your healing surge value. If you are under the effect of your Berserker Fury, you gain the following benefit instead: When you make your next attack roll before the end of your next turn, roll twice and use either result."
  },
  "Slake the Rage": {
    "id": "'15823",
    "action": "No Action",
    "powerClass": "",
    "frequency": "Daily",
    "level": "20",
    "name": "Slake the Rage",
    "type": "Berserker",
    "sourceRef": "Heroes of the Feywild",
    "fullText": "\\r\\n\\r\\n<!DOCTYPE HTML>\\r\\n<html>\\r\\n<head id=\\\"Head1\\\"><title>\\r\\nSlake the Rage\\r\\n</title><meta http-equiv=\\\"X-UA-Compatible\\\" content=\\\"IE=EmulateIE7\\\" /><link href=\\\"styles/detail.css\\\" media=\\\"screen\\\" rel=\\\"stylesheet\\\" type=\\\"text/css\\\" /><link href=\\\"styles/print.css\\\" media=\\\"print\\\" rel=\\\"stylesheet\\\" type=\\\"text/css\\\" /><link href=\\\"styles/mobile.css\\\" media=\\\"handheld\\\" rel=\\\"stylesheet\\\" type=\\\"text/css\\\" />\\r\\n    \\r\\n    \\r\\n    \\r\\n\\r\\n</head>\\r\\n<body>\\r\\n    <form name=\\\"form1\\\" method=\\\"post\\\" action=\\\"display.php?page=power&amp;id=15823\\\" id=\\\"form1\\\">\\r\\n<div>\\r\\n\\r\\n</div>\\r\\n\\r\\n\\r\\n    <div id=\\\"detail\\\">\\r\\n\\r\\n<h1 class=\\\"dailypower\\\"><span class=\\\"level\\\">Deadly Berserker Attack 20</span>Slake the Rage</h1><p class=\\\"flavor\\\"><i>When you enter battle, you are filled with a thirst for violence that can be satisfied only by striking down your foes.</i></p><p class=\\\"powerstat\\\"><b>Daily</b>&nbsp;&nbsp; <img src=\\\"images/bullet.gif\\\" alt=\\\"\\\"/>&nbsp;&nbsp;&nbsp;&nbsp; <b>Martial</b>, <b>Primal</b>, <b>Weapon</b><br/><b>No Action</b>&nbsp;&nbsp;&nbsp;&nbsp;&nbsp;&nbsp;<b>Personal</b> </p><p class=\\\"powerstat\\\"><b>Trigger</b>: You hit a creature with a melee basic weapon attack or a barbarian at-will weapon attack power.</p><p class=\\\"powerstat\\\"><b>Target</b>: The creature you hit</p><p class=\\\"flavor\\\"><b>Effect</b>: The target takes 2[W] extra damage from the triggering attack. Additionally, choose one of the following effects.<br/>&nbsp;&nbsp;&nbsp;&nbsp;<img src=\\\"images/bullet.gif\\\" alt=\\\"\\\"/>&nbsp;&nbsp;&nbsp;&nbsp;The target takes ongoing 10 damage (save ends).<br/>&nbsp;&nbsp;&nbsp;&nbsp;<img src=\\\"images/bullet.gif\\\" alt=\\\"\\\"/>&nbsp;&nbsp;&nbsp;&nbsp;The target is dazed and slowed (save ends both).</p><br/><p class=\\\"publishedIn\\\">Published in <a href=\\\"http://anonym.to/?http://www.wizards.com/dnd/Product.php?x=dnd/products/dndacc/317310000\\\" target=\\\"_new\\\">Heroes of the Feywild</a>, page(s) 116.</p>\\r\\n    </div>\\r\\n    </form>\\r\\n</body>\\r\\n</html>\\r\\n\\r\\n<script type=\\\"text/javascript\\\">\\r\\n    if (document.all) {\\r\\n        if (document.documentMode != 9) {\\r\\n            var ar = document.getElementsByTagName('span'\\r\\n            for (var i = 0; i < ar.length; i++ ) {\\r\\n                var c = ar[i].attributes['class'].value;\\r\\n                if (c == 'milevel')\\r\\n                    ar[i].style.top = \\\"-24px\\\";\\r\\n                else if (c == 'miright')\\r\\n                    ar[i].style.top = \\\"-18px\\\";\\r\\n            }\\r\\n        }\\r\\n    }\\r\\n</script>\\r\\n",
    "class": "Deadly Berserker",
    "flavor": "When you enter battle, you are filled with a thirst for violence that can be satisfied only by striking down your foes.",
    "keywords": [
      "Martial, Primal, Weapon"
    ],
    "range": "Personal </p><p class=\"powerstat\">Trigger: You hit a creature with a melee basic weapon attack or a barbarian at-will weapon attack power.</p><p class=\"powerstat\">Target: The creature you hit</p><p class=\"flavor\">Effect: The target takes 2[W] extra damage from the triggering attack. Additionally, choose one of the following effects.",
    "trigger": "You hit a creature with a melee basic weapon attack or a barbarian at-will weapon attack power.",
    "target": "The creature you hit",
    "effect": "The target takes 2[W] extra damage from the triggering attack. Additionally, choose one of the following effects.<br/>&nbsp;&nbsp;&nbsp;&nbsp;<img src=\"images/bullet.gif\" alt=\"\"/>&nbsp;&nbsp;&nbsp;&nbsp;The target takes ongoing 10 damage (save ends).<br/>&nbsp;&nbsp;&nbsp;&nbsp;<img src=\"images/bullet.gif\" alt=\"\"/>&nbsp;&nbsp;&nbsp;&nbsp;The target is dazed and slowed (save ends both)."
  }
}