{
  "Impaling Strike": {
    "id": "'4178",
    "action": "Standard",
    "powerClass": "Draeven Marauder",
    "frequency": "Encounter",
    "level": "11",
    "name": "Impaling Strike",
    "type": "Marauder",
    "sourceRef": "Dragon Magazine 365",
    "flavor": "You spring into action, expertly strike, and impale your foe on your short pike.",
    "keywords": [
      "Martial, Weapon"
    ],
    "range": "Melee weapon",
    "requirement": "You must be wielding a spear.",
    "special": "Shift up to 3 squares before making the attack.",
    "target": "One creature.",
    "attack": "Strength vs. AC",
    "onHit": "3[W] + Strength modifier damage, and the target is immobilized until the end of your next turn."
  },
  "Exultant Withdrawal": {
    "id": "'4179",
    "action": "Free",
    "powerClass": "Draeven Marauder",
    "frequency": "Encounter",
    "level": "12",
    "name": "Exultant Withdrawal",
    "type": "Marauder",
    "sourceRef": "Dragon Magazine 365",
    "flavor": "Your enemy falls, and you strategically reposition yourself on the battlefield",
    "keywords": [
      "Martial"
    ],
    "range": "Personal",
    "trigger": "One of your attacks drops an enemy to 0 hit points or fewer",
    "effect": "You can shift 3 squares."
  },
  "Taunting Press": {
    "id": "'4180",
    "action": "Standard",
    "powerClass": "Draeven Marauder",
    "frequency": "Daily",
    "level": "20",
    "name": "Taunting Press",
    "type": "Marauder",
    "sourceRef": "Dragon Magazine 365",
    "flavor": "You adroitly outmaneuver your enemy, pushing and baiting him with every stride and strike.",
    "keywords": [
      "Martial, Weapon"
    ],
    "range": "Melee 1",
    "requirement": "You must be wielding a spear (or short pike).",
    "target": "One creature",
    "effect": "Until the end of the encounter, as long as you are adjacent to the target, you slide the target 1 square before making a melee attack against it.",
    "attack": "Strength vs. AC",
    "onHit": "4[W] + Strength modifier damage."
  }
}