{
  "Starshine upon the People": {
    "id": "'4785",
    "action": "Minor",
    "powerClass": "Elf High Mage",
    "frequency": "Daily",
    "level": "26",
    "name": "Starshine upon the People",
    "type": "High",
    "sourceRef": "Dragon Magazine 367",
    "flavor": "You summon a shower of glittering stardust that drifts down over your allies, reinvigorating them and heartening them for the battle.",
    "keywords": [
      "Arcane"
    ],
    "range": "Close burst 10",
    "target": "Each ally in the burst",
    "effect": "The targets can spend a healing surge and immediately make a saving throw against one condition affecting them that a save can end. In addition, eladrin, elves, and half-elves affected by the power gain a +1 power bonus to attack rolls until the end of the encounter."
  }
}