{
  "Implacable Destruction": {
    "id": "'4775",
    "action": "Minor",
    "powerClass": "Eternal Defender",
    "frequency": "Daily",
    "level": "26",
    "name": "Implacable Destruction",
    "type": "Defender",
    "sourceRef": "Martial Power",
    "flavor": "You take on a defiant aspect that makes it impossible for your enemies to avoid your attacks completely.",
    "keywords": [
      "Martial, Stance"
    ],
    "range": "Personal",
    "effect": "Until the stance ends, every time you miss with a melee or a close weapon attack, you deal damage to the target equal to your Strength modifier."
  }
}