{
  "Moment of Triumph": {
    "id": "'10569",
    "action": "Minor",
    "powerClass": "Glorious Myrmidon",
    "frequency": "Daily",
    "level": "20",
    "name": "Moment of Triumph",
    "type": "Myrmidon",
    "sourceRef": "Martial Power 2",
    "flavor": "You exhibit a level of pure skill and resilience that few opponents can match, especially in single combat.",
    "keywords": [
      "Martial, Stance"
    ],
    "range": "Personal",
    "effect": "Until the stance ends, you gain a +2 power bonus to attack rolls and to all defenses. In addition, enemies marked by you take a -4 penalty to attack rolls instead of a -2 penalty for making an attack that doesn’t include you as a target."
  },
  "Exult in Victory": {
    "id": "'10570",
    "action": "Free",
    "powerClass": "Glorious Myrmidon",
    "frequency": "Encounter",
    "level": "12",
    "name": "Exult in Victory",
    "type": "Myrmidon",
    "sourceRef": "Martial Power 2",
    "flavor": "The glory of a hard-fought victory sweeps away your fatigue when you defeat a worthy foe.",
    "keywords": [
      "Healing, Martial"
    ],
    "range": "Personal",
    "trigger": "You reduce an enemy to 0 hit points with a melee attack",
    "effect": "You use your second wind, and you gain a +1 bonus to attack rolls until the end of your next turn."
  },
  "Charge To Glory": {
    "id": "'138",
    "action": "Standard",
    "powerClass": "Glorious Myrmidon",
    "frequency": "Encounter",
    "level": "11",
    "name": "Charge To Glory",
    "type": "Myrmidon",
    "sourceRef": "Martial Power 2",
    "flavor": "You barrel into your enemy, eager to draw first blood.",
    "keywords": [
      "Martial, Weapon"
    ],
    "range": "Melee weapon",
    "target": "One creature",
    "attack": "Strength vs. AC",
    "onHit": "2[W] + Strength modifier damage.",
    "effect": "You knock the target prone.",
    "special": "When charging, you can use this power in place of a melee basic attack."
  }
}