{
  "Toss and Close": {
    "id": "'6027",
    "action": "Standard",
    "powerClass": "",
    "frequency": "Encounter",
    "level": "11",
    "name": "Toss and Close",
    "type": "Giantkiller",
    "sourceRef": "Dragon Magazine 370",
    "fullText": "\\r\\n\\r\\n<!DOCTYPE HTML>\\r\\n<html>\\r\\n<head id=\\\"Head1\\\"><title>\\r\\nToss and Close\\r\\n</title><meta http-equiv=\\\"X-UA-Compatible\\\" content=\\\"IE=EmulateIE7\\\" /><link href=\\\"styles/detail.css\\\" media=\\\"screen\\\" rel=\\\"stylesheet\\\" type=\\\"text/css\\\" /><link href=\\\"styles/print.css\\\" media=\\\"print\\\" rel=\\\"stylesheet\\\" type=\\\"text/css\\\" /><link href=\\\"styles/mobile.css\\\" media=\\\"handheld\\\" rel=\\\"stylesheet\\\" type=\\\"text/css\\\" />\\r\\n    \\r\\n    \\r\\n    \\r\\n\\r\\n</head>\\r\\n<body>\\r\\n    <form name=\\\"form1\\\" method=\\\"post\\\" action=\\\"display.php?page=power&amp;id=6027\\\" id=\\\"form1\\\">\\r\\n<div>\\r\\n\\r\\n</div>\\r\\n\\r\\n\\r\\n    <div id=\\\"detail\\\">\\r\\n\\r\\n<h1 class=\\\"encounterpower\\\"><span class=\\\"level\\\">Oman Giantkiller Attack 11</span>Toss and Close</h1><p class=\\\"flavor\\\"><i>You throw your weapon at the target, rapidly close the ground between you and it, and get in a quick melee attack.</i></p><p class=\\\"powerstat\\\"><b>Encounter</b>&nbsp;&nbsp; <img src=\\\"images/bullet.gif\\\" alt=\\\"\\\"/>&nbsp;&nbsp;&nbsp;&nbsp; <b>Martial</b>, <b>Weapon</b><br/><b>Standard Action</b>&nbsp;&nbsp;&nbsp;&nbsp;&nbsp;&nbsp;<b>Ranged</b> weapon</p><p class=\\\"flavor\\\"><b>Requirement</b>: You must be wielding a light thrown or heavy thrown weapon.</p><p class=\\\"powerstat\\\"><b>Target</b>: One creature</p><p class=\\\"powerstat\\\"><b>Attack</b>: Strength vs. AC</p><p class=\\\"flavor\\\"><b>Hit</b>: 2[W] + Strength modifier damage</p><p class=\\\"powerstat\\\"><b>Effect</b>: After the attack is resolved, move your speed toward the target of your ranged attack; you can draw one melee weapon during this movement. If you are within melee range at the end of this movement, make a melee basic attack against the target.</p><br/><p class=\\\"publishedIn\\\">Published in <a href=\\\"http://anonym.to/?http://www.wizards.com/default.asp?x=dnd/drtoc/370\\\" target=\\\"_new\\\">Dragon Magazine 370</a>, page(s) 39.</p>\\r\\n    </div>\\r\\n    </form>\\r\\n</body>\\r\\n</html>\\r\\n\\r\\n<script type=\\\"text/javascript\\\">\\r\\n    if (document.all) {\\r\\n        if (document.documentMode != 9) {\\r\\n            var ar = document.getElementsByTagName('span'\\r\\n            for (var i = 0; i < ar.length; i++ ) {\\r\\n                var c = ar[i].attributes['class'].value;\\r\\n                if (c == 'milevel')\\r\\n                    ar[i].style.top = \\\"-24px\\\";\\r\\n                else if (c == 'miright')\\r\\n                    ar[i].style.top = \\\"-18px\\\";\\r\\n            }\\r\\n        }\\r\\n    }\\r\\n</script>\\r\\n",
    "class": "Oman Giantkiller",
    "flavor": "You throw your weapon at the target, rapidly close the ground between you and it, and get in a quick melee attack.",
    "keywords": [
      "Martial, Weapon"
    ],
    "range": "Ranged weapon</p><p class=\"flavor\">Requirement: You must be wielding a light thrown or heavy thrown weapon.</p><p class=\"powerstat\">Target: One creature</p><p class=\"powerstat\">Attack: Strength vs. AC</p><p class=\"flavor\">Hit: 2[W] + Strength modifier damage</p><p class=\"powerstat\">Effect: After the attack is resolved, move your speed toward the target of your ranged attack; you can draw one melee weapon during this movement. If you are within melee range at the end of this movement, make a melee basic attack against the target.</p>",
    "requirement": "You must be wielding a light thrown or heavy thrown weapon.",
    "target": "One creature",
    "attack": "Strength vs. AC",
    "onHit": "2[W] + Strength modifier damage",
    "effect": "After the attack is resolved, move your speed toward the target of your ranged attack; you can draw one melee weapon during this movement. If you are within melee range at the end of this movement, make a melee basic attack against the target."
  },
  "Focused Assault": {
    "id": "'6184",
    "action": "Free",
    "powerClass": "",
    "frequency": "Daily",
    "level": "12",
    "name": "Focused Assault",
    "type": "Giantkiller",
    "sourceRef": "Dragon Magazine 370",
    "fullText": "\\r\\n\\r\\n<!DOCTYPE HTML>\\r\\n<html>\\r\\n<head id=\\\"Head1\\\"><title>\\r\\nFocused Assault\\r\\n</title><meta http-equiv=\\\"X-UA-Compatible\\\" content=\\\"IE=EmulateIE7\\\" /><link href=\\\"styles/detail.css\\\" media=\\\"screen\\\" rel=\\\"stylesheet\\\" type=\\\"text/css\\\" /><link href=\\\"styles/print.css\\\" media=\\\"print\\\" rel=\\\"stylesheet\\\" type=\\\"text/css\\\" /><link href=\\\"styles/mobile.css\\\" media=\\\"handheld\\\" rel=\\\"stylesheet\\\" type=\\\"text/css\\\" />\\r\\n    \\r\\n    \\r\\n    \\r\\n\\r\\n</head>\\r\\n<body>\\r\\n    <form name=\\\"form1\\\" method=\\\"post\\\" action=\\\"display.php?page=power&amp;id=6184\\\" id=\\\"form1\\\">\\r\\n<div>\\r\\n\\r\\n</div>\\r\\n\\r\\n\\r\\n    <div id=\\\"detail\\\">\\r\\n\\r\\n<h1 class=\\\"dailypower\\\"><span class=\\\"level\\\">Oman Giantkiller Utility 12</span>Focused Assault</h1><p class=\\\"flavor\\\"><i>You spend a moment refocusing your fury and can attack the enemy with renewed vigor.</i></p><p class=\\\"powerstat\\\"><b>Daily</b>&nbsp;&nbsp; <img src=\\\"images/bullet.gif\\\" alt=\\\"\\\"/>&nbsp;&nbsp;&nbsp;&nbsp; <b>Martial</b><br/><b>Free Action</b>&nbsp;&nbsp;&nbsp;&nbsp;&nbsp;&nbsp;<b>Close</b> burst 5</p><p class=\\\"powerstat\\\"><b>Target</b>: One creature in the burst</p><p class=\\\"flavor\\\"><b>Effect</b>: The target is considered your quarry and is marked by you until the end of your next turn.</p><br/><p class=\\\"publishedIn\\\">Published in <a href=\\\"http://anonym.to/?http://www.wizards.com/default.asp?x=dnd/drtoc/370\\\" target=\\\"_new\\\">Dragon Magazine 370</a>, page(s) 39.</p>\\r\\n    </div>\\r\\n    </form>\\r\\n</body>\\r\\n</html>\\r\\n\\r\\n<script type=\\\"text/javascript\\\">\\r\\n    if (document.all) {\\r\\n        if (document.documentMode != 9) {\\r\\n            var ar = document.getElementsByTagName('span'\\r\\n            for (var i = 0; i < ar.length; i++ ) {\\r\\n                var c = ar[i].attributes['class'].value;\\r\\n                if (c == 'milevel')\\r\\n                    ar[i].style.top = \\\"-24px\\\";\\r\\n                else if (c == 'miright')\\r\\n                    ar[i].style.top = \\\"-18px\\\";\\r\\n            }\\r\\n        }\\r\\n    }\\r\\n</script>\\r\\n",
    "class": "Oman Giantkiller",
    "flavor": "You spend a moment refocusing your fury and can attack the enemy with renewed vigor.",
    "keywords": [
      "Martial"
    ],
    "range": "Close burst 5</p><p class=\"powerstat\">Target: One creature in the burst</p><p class=\"flavor\">Effect: The target is considered your quarry and is marked by you until the end of your next turn.</p>",
    "target": "One creature in the burst",
    "effect": "The target is considered your quarry and is marked by you until the end of your next turn."
  },
  "Coordinated Devastation": {
    "id": "'6185",
    "action": "Standard",
    "powerClass": "",
    "frequency": "Daily",
    "level": "20",
    "name": "Coordinated Devastation",
    "type": "Giantkiller",
    "sourceRef": "Dragon Magazine 370",
    "fullText": "\\r\\n\\r\\n<!DOCTYPE HTML>\\r\\n<html>\\r\\n<head id=\\\"Head1\\\"><title>\\r\\nCoordinated Devastation\\r\\n</title><meta http-equiv=\\\"X-UA-Compatible\\\" content=\\\"IE=EmulateIE7\\\" /><link href=\\\"styles/detail.css\\\" media=\\\"screen\\\" rel=\\\"stylesheet\\\" type=\\\"text/css\\\" /><link href=\\\"styles/print.css\\\" media=\\\"print\\\" rel=\\\"stylesheet\\\" type=\\\"text/css\\\" /><link href=\\\"styles/mobile.css\\\" media=\\\"handheld\\\" rel=\\\"stylesheet\\\" type=\\\"text/css\\\" />\\r\\n    \\r\\n    \\r\\n    \\r\\n\\r\\n</head>\\r\\n<body>\\r\\n    <form name=\\\"form1\\\" method=\\\"post\\\" action=\\\"display.php?page=power&amp;id=6185\\\" id=\\\"form1\\\">\\r\\n<div>\\r\\n\\r\\n</div>\\r\\n\\r\\n\\r\\n    <div id=\\\"detail\\\">\\r\\n\\r\\n<h1 class=\\\"dailypower\\\"><span class=\\\"level\\\">Oman Giantkiller Attack 20</span>Coordinated Devastation</h1><p class=\\\"flavor\\\"><i>You slice into the enemy, creating a gaping wound that is easy for your allies to target with their attacks.</i></p><p class=\\\"powerstat\\\"><b>Daily</b>&nbsp;&nbsp; <img src=\\\"images/bullet.gif\\\" alt=\\\"\\\"/>&nbsp;&nbsp;&nbsp;&nbsp; <b>Martial</b>, <b>Weapon</b><br/><b>Standard Action</b>&nbsp;&nbsp;&nbsp;&nbsp;&nbsp;&nbsp;<b>Melee</b> weapon</p><p class=\\\"flavor\\\"><b>Requirement</b>: You must be wielding two melee weapons.</p><p class=\\\"powerstat\\\"><b>Target</b>: One creature</p><p class=\\\"powerstat\\\"><b>Attack</b>: Strength vs. AC (main weapon and off-hand weapon), two attacks</p><p class=\\\"flavor\\\"><b>Hit</b>: 2[W] + Strength modifier damage per attack. If both attacks hit, all allies score critical hits against the target on rolls of 18 or higher until the end of your next turn.<br/>If the target is Large or larger and at least one attack hits, all allies score critical hits against the target on rolls of 17 or higher until the end of your next turn.</p><br/><p class=\\\"publishedIn\\\">Published in <a href=\\\"http://anonym.to/?http://www.wizards.com/default.asp?x=dnd/drtoc/370\\\" target=\\\"_new\\\">Dragon Magazine 370</a>, page(s) 39.</p>\\r\\n    </div>\\r\\n    </form>\\r\\n</body>\\r\\n</html>\\r\\n\\r\\n<script type=\\\"text/javascript\\\">\\r\\n    if (document.all) {\\r\\n        if (document.documentMode != 9) {\\r\\n            var ar = document.getElementsByTagName('span'\\r\\n            for (var i = 0; i < ar.length; i++ ) {\\r\\n                var c = ar[i].attributes['class'].value;\\r\\n                if (c == 'milevel')\\r\\n                    ar[i].style.top = \\\"-24px\\\";\\r\\n                else if (c == 'miright')\\r\\n                    ar[i].style.top = \\\"-18px\\\";\\r\\n            }\\r\\n        }\\r\\n    }\\r\\n</script>\\r\\n",
    "class": "Oman Giantkiller",
    "flavor": "You slice into the enemy, creating a gaping wound that is easy for your allies to target with their attacks.",
    "keywords": [
      "Martial, Weapon"
    ],
    "range": "Melee weapon</p><p class=\"flavor\">Requirement: You must be wielding two melee weapons.</p><p class=\"powerstat\">Target: One creature</p><p class=\"powerstat\">Attack: Strength vs. AC (main weapon and off-hand weapon), two attacks</p><p class=\"flavor\">Hit: 2[W] + Strength modifier damage per attack. If both attacks hit, all allies score critical hits against the target on rolls of 18 or higher until the end of your next turn.",
    "requirement": "You must be wielding two melee weapons.",
    "target": "One creature",
    "attack": "Strength vs. AC (main weapon and off-hand weapon), two attacks",
    "onHit": "2[W] + Strength modifier damage per attack. If both attacks hit, all allies score critical hits against the target on rolls of 18 or higher until the end of your next turn.<br/>If the target is Large or larger and at least one attack hits, all allies score critical hits against the target on rolls of 17 or higher until the end of your next turn."
  }
}