{
  "id": "'785",
  "type": "Campaign",
  "campaign": "Neverwinter",
  "skills": "Bluff, Dungeoneering, Stealth",
  "sourceRef": "Neverwinter Campaign Setting",
  "fullText": "\\r\\n\\r\\n<!DOCTYPE HTML>\\r\\n<html>\\r\\n<head id=\\\"Head1\\\"><title>\\r\\nBregan D'aerthe Spy\\r\\n</title><meta http-equiv=\\\"X-UA-Compatible\\\" content=\\\"IE=EmulateIE7\\\" /><link href=\\\"styles/detail.css\\\" media=\\\"screen\\\" rel=\\\"stylesheet\\\" type=\\\"text/css\\\" /><link href=\\\"styles/print.css\\\" media=\\\"print\\\" rel=\\\"stylesheet\\\" type=\\\"text/css\\\" /><link href=\\\"styles/mobile.css\\\" media=\\\"handheld\\\" rel=\\\"stylesheet\\\" type=\\\"text/css\\\" />\\r\\n    \\r\\n    \\r\\n    \\r\\n\\r\\n</head>\\r\\n<body>\\r\\n    <form name=\\\"form1\\\" method=\\\"post\\\" action=\\\"display.php?page=background&amp;id=785\\\" id=\\\"form1\\\">\\r\\n<div>\\r\\n\\r\\n</div>\\r\\n\\r\\n\\r\\n    <div id=\\\"detail\\\">\\r\\n\\r\\n<h1   class=\\\"player\\\">Bregan D'aerthe Spy</h1><p class=\\\"flavortext\\\"><b>Type: </b>Campaign<br/><b>Campaign Setting: </b>Neverwinter<br/><b>Prerequisite: </b>Drow<br/></p>Drow train in stealth and the lore of the Underdark from a young age, and they rely upon falsehood as much as other creatures do upon breathing. As a member of Bregan D’aerthe, you are well versed in one of the skills vital to your survival amid the deadly politics and dangerous pockets of the Underdark.<br/>&nbsp;&nbsp;&nbsp;&nbsp;<i>Associated Skills: </i>Bluff, Dungeoneering, Stealth<br/><p class=\\\"publishedIn\\\">Published in <a href=\\\"http://anonym.to/?http://www.wizards.com/dnd/Product.php?x=dnd/products/dndacc/317290000\\\" target=\\\"_new\\\">Neverwinter Campaign Setting</a>, page(s) 45.</p>\\r\\n    </div>\\r\\n    </form>\\r\\n</body>\\r\\n</html>\\r\\n\\r\\n<script type=\\\"text/javascript\\\">\\r\\n    if (document.all) {\\r\\n        if (document.documentMode != 9) {\\r\\n            var ar = document.getElementsByTagName('span'\\r\\n            for (var i = 0; i < ar.length; i++ ) {\\r\\n                var c = ar[i].attributes['class'].value;\\r\\n                if (c == 'milevel')\\r\\n                    ar[i].style.top = \\\"-24px\\\";\\r\\n                else if (c == 'miright')\\r\\n                    ar[i].style.top = \\\"-18px\\\";\\r\\n            }\\r\\n        }\\r\\n    }\\r\\n</script>\\r\\n');\n",
  "flavor": "Drow train in stealth and the lore of the Underdark from a young age, and they rely upon falsehood as much as other creatures do upon breathing. As a member of Bregan D’aerthe, you are well versed in one of the skills vital to your survival amid the deadly politics and dangerous pockets of the Underdark.",
  "name": "Bregan D'aerthe Spy"
}