{
  "id": "'145",
  "type": "Occupation",
  "campaign": "General",
  "skills": "Insight, Perception, or the knowledge skill that b",
  "sourceRef": "Dragon Magazine 373",
  "flavor": "You fought and killed your people’s enemies. What sorts of creatures do you define as enemies of your people? Do you target members of a humanoid race, such as goblins? Or do you hunt monstrous threats such as aberrant horrors or undead? How does your long experience fighting these creatures shape your personality? How do you react when you encounter your favored enemy?",
  "name": "Occupation - Foe Killer"
}