{
  "Channel the Signature": {
    "id": "'6926",
    "action": "Minor",
    "powerClass": "Archspell",
    "frequency": "Encounter",
    "level": "26",
    "name": "Channel the Signature",
    "type": "Utility",
    "sourceRef": "Arcane Power",
    "flavor": "You bring the power of your signature spell to your lips, but rather than casting it, you hold it resonating in your mind. Until you cast it, you siphon energy to resist the attacks of others.",
    "keywords": [
      "Arcane"
    ],
    "range": "Personal",
    "effect": "You gain resist 15 to all damage until the end of the encounter or until you use your Signature Spell."
  }
}