{
    "id": "'93",
    "level": "8",
    "price": "250 gp",
    "keySkill": "Arcana (no check)",
    "sourceRef": "Forgotten Realms Player's Guide",
    "name": "\\r\\n<html>\\r\\n<head id=\\\"Head1\\\"><title>\\r\\nStatus\\r\\n</title><meta http-equiv=\\\"X-UA-Compatible\\\" content=\\\"IE=EmulateIE7\\\" /><link href=\\\"styles/detail.css\\\" media=\\\"screen\\\" rel=\\\"stylesheet\\\" type=\\\"text/css\\\" /><link href=\\\"styles/print.css\\\" media=\\\"print\\\" rel=\\\"stylesheet\\\" type=\\\"text/css\\\" /><link href=\\\"styles/mobile.css\\\" media=\\\"handheld\\\" rel=\\\"stylesheet\\\" type=\\\"text/css\\\" />\\r\\n    \\r\\n    \\r\\n    \\r\\n\\r\\n</head>\\r\\n<body>\\r\\n    <form name=\\\"form1\\\" method=\\\"post\\\" action=\\\"display.php?page=ritual&amp;id=93\\\" id=\\\"form1\\\">\\r\\n<div>\\r\\n\\r\\n</div>\\r\\n\\r\\n\\r\\n    <div id=\\\"detail\\\">\\r\\n\\r\\n<h1 class=\\\"player\\\">Status",
    "flavorText": "You and at least one other individual consume the foultasting  brew, dregs and all. At the end of the ritual, you feel uncommonly close, as if you shared some bond with your ally.",
    "category": "Divination",
    "time": "10 minutes",
    "duration": "24 hours",
    "text": "You and up to eight ritual participants gain a powerful connection to one another. For the ritual’s duration, you know the current hit point total, healing surges remaining, and the nature of any persistent conditions affecting any other ritual participant. The connection persists at any distance except across planes.",
    "componentCost": "135 gp"
}