{
    "id": "'2285",
    "tier": "Heroic",
    "refSource": "Player's Handbook Races: Tiefling",
    "sort": "1",
    "name": "Ancient Covenant of Nessus",
    "prerequisite": "Tiefling, invoker, Divine Covenant class feature",
    "benefit": "When you use a divine encounter or daily attack power on your turn, instead of your normal covenant manifestation, you can allow one target of the power to make a basic attack as a free action. If the target makes this attack, it takes fire damage equal to 5 + your Intelligence modifier after resolving the attack."
}