{
    "id": "'1234",
    "tier": "Heroic",
    "refSource": "Dragon Magazine Annual, Dragon Magazine 372",
    "sort": "1",
    "name": "Deathward Aegis",
    "prerequisite": "Shadar-kai, swordmage, Aegis of Shielding class feature",
    "benefit": "When you reduce damage with your Aegis of Shielding class feature, the same target also gains resist necrotic 5 until the end of its next turn. Increase this resistance to resist necrotic 10 at 11th level, and again to resist necrotic 15 at 21st level."
}