{
    "id": "'1521",
    "featName": "Elemental Rebuke",
    "tier": "Heroic",
    "refSource": "Divine Power",
    "fullText": "\\r\\n\\r\\n<!DOCTYPE HTML>\\r\\n<html>\\r\\n<head id=\\\"Head1\\\"><title>\\r\\nElemental Rebuke\\r\\n</title><meta http-equiv=\\\"X-UA-Compatible\\\" content=\\\"IE=EmulateIE7\\\" /><link href=\\\"styles/detail.css\\\" media=\\\"screen\\\" rel=\\\"stylesheet\\\" type=\\\"text/css\\\" /><link href=\\\"styles/print.css\\\" media=\\\"print\\\" rel=\\\"stylesheet\\\" type=\\\"text/css\\\" /><link href=\\\"styles/mobile.css\\\" media=\\\"handheld\\\" rel=\\\"stylesheet\\\" type=\\\"text/css\\\" />\\r\\n    \\r\\n    \\r\\n    \\r\\n\\r\\n</head>\\r\\n<body>\\r\\n    <form name=\\\"form1\\\" method=\\\"post\\\" action=\\\"display.php?page=feat&amp;id=1521\\\" id=\\\"form1\\\">\\r\\n<div>\\r\\n\\r\\n</div>\\r\\n\\r\\n\\r\\n    <div id=\\\"detail\\\">\\r\\n\\r\\n<h1 class=\\\"player\\\">Elemental Rebuke</h1><p class=\\\"flavor\\\"><b>Heroic Tier</b><br/><b>Prerequisite</b>: Genasi, invoker, Covenant of Preservation class feature<br/><b>Benefit</b>: When you use your preserver’s rebuke power, you also grant a bonus to the ally attacked by the triggering enemy based on your current elemental manifestation.<br/>Earthsoul: The ally gains a +1 power bonus to Fortitude and to saving throws until the start of your next turn.<br/>Firesoul: The ally gains a +1 power bonus to Reflex and resist 5 fire until the start of your next turn.<br/>Stormsoul: The ally gains a +1 power bonus to Fortitude and resist 5 lightning until the start of your next turn.<br/>Watersoul: The ally gains a +5 power bonus to saving throws against ongoing damage until the start of your next turn.<br/>Windsoul: The ally gains a +1 power bonus to speed and resist 5 cold until the start of your next turn.<br/></p><p class=\\\"publishedIn\\\">Published in <a href=\\\"http://anonym.to/?http://www.wizards.com/default.asp?x=products/dndacc/9780786949823\\\" target=\\\"_new\\\">Divine Power</a>, page(s) 134.</p>\\r\\n    </div>\\r\\n    </form>\\r\\n</body>\\r\\n</html>",
    "sort": "1",
    "name": "Elemental Rebuke",
    "prerequisite": "Genasi, invoker, Covenant of Preservation class feature",
    "benefit": "When you use your preserver’s rebuke power, you also grant a bonus to the ally attacked by the triggering enemy based on your current elemental manifestation."
}