{
    "id": "'1574",
    "featName": "Focused Wrath",
    "tier": "Paragon",
    "refSource": "Divine Power",
    "fullText": "\\r\\n\\r\\n<!DOCTYPE HTML>\\r\\n<html>\\r\\n<head id=\\\"Head1\\\"><title>\\r\\nFocused Wrath\\r\\n</title><meta http-equiv=\\\"X-UA-Compatible\\\" content=\\\"IE=EmulateIE7\\\" /><link href=\\\"styles/detail.css\\\" media=\\\"screen\\\" rel=\\\"stylesheet\\\" type=\\\"text/css\\\" /><link href=\\\"styles/print.css\\\" media=\\\"print\\\" rel=\\\"stylesheet\\\" type=\\\"text/css\\\" /><link href=\\\"styles/mobile.css\\\" media=\\\"handheld\\\" rel=\\\"stylesheet\\\" type=\\\"text/css\\\" />\\r\\n    \\r\\n    \\r\\n    \\r\\n\\r\\n</head>\\r\\n<body>\\r\\n    <form name=\\\"form1\\\" method=\\\"post\\\" action=\\\"display.php?page=feat&amp;id=1574\\\" id=\\\"form1\\\">\\r\\n<div>\\r\\n\\r\\n</div>\\r\\n\\r\\n\\r\\n    <div id=\\\"detail\\\">\\r\\n\\r\\n<h1 class=\\\"player\\\">Focused Wrath</h1><p class=\\\"flavor\\\"><b>Paragon Tier</b><br/><b>Prerequisite</b>: 11th level, invoker, Covenant of Wrath class feature<br/><b>Benefit</b>: When you use your armor of wrath power and the triggering enemy is the only enemy in the burst, you deal 1d6 extra damage with that power.<br/>At 21st level, this extra damage increases to 2d6.<br/></p><p class=\\\"publishedIn\\\">Published in <a href=\\\"http://anonym.to/?http://www.wizards.com/default.asp?x=products/dndacc/9780786949823\\\" target=\\\"_new\\\">Divine Power</a>, page(s) 138.</p>\\r\\n    </div>\\r\\n    </form>\\r\\n</body>\\r\\n</html>",
    "sort": "2",
    "name": "Focused Wrath",
    "prerequisite": "11th level, invoker, Covenant of Wrath class feature",
    "benefit": "When you use your armor of wrath power and the triggering enemy is the only enemy in the burst, you deal 1d6 extra damage with that power."
}