{
    "id": "'3246",
    "featName": "Urikite Staff Practice",
    "tier": "Heroic",
    "refSource": "Dark Sun Campaign Setting",
    "fullText": "\\r\\n\\r\\n<!DOCTYPE HTML>\\r\\n<html>\\r\\n<head id=\\\"Head1\\\"><title>\\r\\nUrikite Staff Practice\\r\\n</title><meta http-equiv=\\\"X-UA-Compatible\\\" content=\\\"IE=EmulateIE7\\\" /><link href=\\\"styles/detail.css\\\" media=\\\"screen\\\" rel=\\\"stylesheet\\\" type=\\\"text/css\\\" /><link href=\\\"styles/print.css\\\" media=\\\"print\\\" rel=\\\"stylesheet\\\" type=\\\"text/css\\\" /><link href=\\\"styles/mobile.css\\\" media=\\\"handheld\\\" rel=\\\"stylesheet\\\" type=\\\"text/css\\\" />\\r\\n    \\r\\n    \\r\\n    \\r\\n\\r\\n</head>\\r\\n<body>\\r\\n    <form name=\\\"form1\\\" method=\\\"post\\\" action=\\\"display.php?page=feat&amp;id=3246\\\" id=\\\"form1\\\">\\r\\n<div>\\r\\n\\r\\n</div>\\r\\n\\r\\n\\r\\n    <div id=\\\"detail\\\">\\r\\n\\r\\n<h1 class=\\\"player\\\">Urikite Staff Practice [Arena Fighting]</h1><p class=\\\"flavor\\\"><b>Heroic Tier</b><br/><b>Prerequisite</b>: Any martial class<br/><b>Benefit</b>: You gain a +2 feat bonus to Stealth checks.<br/>&nbsp;&nbsp;&nbsp;&nbsp;When you use a power associated with this feat and hit an enemy with it, the next attack that hits that enemy before the end of your next turn deals 3 extra damage.<br/></p><br />Associated Powers: <a href=\\\"power.php?id=10470\\\">Grappling Strike</a>, <a href=\\\"power.php?id=1505\\\">Hit and Run</a>, <a href=\\\"power.php?id=653\\\">Riposte Strike</a>, <a href=\\\"power.php?id=1063\\\">Viper’s Strike</a><br /><p class=\\\"publishedIn\\\">Published in <a href=\\\"http://anonym.to/?http://www.wizards.com/dnd/Product.php?x=dnd/products/dndacc/253870000\\\" target=\\\"_new\\\">Dark Sun Campaign Setting</a>, page(s) 112.</p>\\r\\n    </div>\\r\\n    </form>\\r\\n</body>\\r\\n</html>",
    "sort": "1",
    "name": "Urikite Staff Practice",
    "prerequisite": "Any martial class",
    "benefit": "You gain a +2 feat bonus to Stealth checks."
}